gnost/__init__.py
gnost/cli/__init__.py
gnost/cli/app.py
gnost/cli/commands/__init__.py
gnost/cli/commands/onboard.py
gnost/config/__init__.py
gnost/config/languages.py
gnost/core/__init__.py
gnost/core/counter.py
gnost/core/flow.py
gnost/core/graph.py
gnost/core/ranker.py
gnost/languages/base.py
gnost/languages/java.py
gnost/languages/javascript.py
gnost/languages/python.py
gnost/languages/typescript.py
gnost/plugins/__init__.py
gnost/plugins/base.py
gnost/reporters/__init__.py
gnost/reporters/files.py
gnost/reporters/folders.py
gnost/reporters/loc_summary.py
gnost/reporters/markdown.py
gnost/reporters/mermaid.py
gnost/reporters/stats.py
gnost/reporters/summary.py
gnost/scanner/__init__.py
gnost/scanner/classify.py
gnost/scanner/engine.py
gnost/scanner/filters.py
gnost/scanner/loc.py
gnost/scanner/models.py
gnost/utils/__init__.py
gnost/utils/printer.py
gnost/utils/progress.py
gnost-0.1.2.dist-info/licenses/LICENSE
gnost-0.1.2.dist-info/METADATA
gnost-0.1.2.dist-info/WHEEL
gnost-0.1.2.dist-info/entry_points.txt
gnost-0.1.2.dist-info/top_level.txt
gnost-0.1.2.dist-info/RECORD
