Metadata-Version: 2.4
Name: gnost
Version: 0.1.2
Summary: GNOST — Codebase Knowledge
Author-email: Mohd Zain <zainmohd1998@gmail.com>
License: MIT License
Project-URL: Documentation, https://gnost.readthedocs.io
Project-URL: Source, https://github.com/mohdzain98/gnost
Project-URL: Issues, https://github.com/mohdzain98/gnost/issues
Classifier: Programming Language :: Python :: 3
Classifier: Programming Language :: Python :: 3.9
Classifier: Programming Language :: Python :: 3.10
Classifier: Programming Language :: Python :: 3.11
Classifier: License :: OSI Approved :: MIT License
Classifier: Operating System :: OS Independent
Requires-Python: >=3.8
License-File: LICENSE
Requires-Dist: rich
Requires-Dist: tqdm
Dynamic: license-file
